cbbd/__init__.py
cbbd/api_client.py
cbbd/api_response.py
cbbd/configuration.py
cbbd/exceptions.py
cbbd/py.typed
cbbd/rest.py
cbbd/api/__init__.py
cbbd/api/conferences_api.py
cbbd/api/draft_api.py
cbbd/api/games_api.py
cbbd/api/lines_api.py
cbbd/api/lineups_api.py
cbbd/api/plays_api.py
cbbd/api/rankings_api.py
cbbd/api/ratings_api.py
cbbd/api/recruiting_api.py
cbbd/api/stats_api.py
cbbd/api/teams_api.py
cbbd/api/venues_api.py
cbbd/models/__init__.py
cbbd/models/adjusted_efficiency_info.py
cbbd/models/adjusted_efficiency_info_rankings.py
cbbd/models/conference_history.py
cbbd/models/conference_history_teams_inner.py
cbbd/models/conference_info.py
cbbd/models/draft_pick.py
cbbd/models/draft_position.py
cbbd/models/draft_team.py
cbbd/models/game_box_score_players.py
cbbd/models/game_box_score_players_players_inner.py
cbbd/models/game_box_score_team.py
cbbd/models/game_box_score_team_stats.py
cbbd/models/game_box_score_team_stats_points.py
cbbd/models/game_info.py
cbbd/models/game_line_info.py
cbbd/models/game_lines.py
cbbd/models/game_media_info.py
cbbd/models/game_media_info_broadcasts_inner.py
cbbd/models/game_status.py
cbbd/models/line_provider_info.py
cbbd/models/lineup_stats.py
cbbd/models/lineup_unit_stats.py
cbbd/models/lineup_unit_stats_four_factors.py
cbbd/models/lineup_unit_stats_two_pointers.py
cbbd/models/play_info.py
cbbd/models/play_info_on_floor_inner.py
cbbd/models/play_info_participants_inner.py
cbbd/models/play_type_info.py
cbbd/models/player_season_shooting_stats.py
cbbd/models/player_season_stats.py
cbbd/models/player_season_stats_win_shares.py
cbbd/models/player_subsititution.py
cbbd/models/player_subsititution_sub_in.py
cbbd/models/poll_team_info.py
cbbd/models/recruit.py
cbbd/models/recruit_committed_to.py
cbbd/models/recruit_hometown.py
cbbd/models/season_shooting_stats.py
cbbd/models/season_shooting_stats_attempts_breakdown.py
cbbd/models/season_shooting_stats_dunks.py
cbbd/models/season_type.py
cbbd/models/shooting_stats.py
cbbd-1.22.4.dist-info/METADATA
cbbd-1.22.4.dist-info/WHEEL
cbbd-1.22.4.dist-info/top_level.txt
cbbd-1.22.4.dist-info/RECORD
